spacetraders/__init__.py
spacetraders/api/__init__.py
spacetraders/api/agents/__init__.py
spacetraders/api/agents/get_agent.py
spacetraders/api/agents/get_agents.py
spacetraders/api/agents/get_my_agent.py
spacetraders/api/contracts/__init__.py
spacetraders/api/contracts/accept_contract.py
spacetraders/api/contracts/deliver_contract.py
spacetraders/api/contracts/fulfill_contract.py
spacetraders/api/contracts/get_contract.py
spacetraders/api/contracts/get_contracts.py
spacetraders/api/default/__init__.py
spacetraders/api/default/get_status.py
spacetraders/api/default/register.py
spacetraders/api/factions/__init__.py
spacetraders/api/factions/get_faction.py
spacetraders/api/factions/get_factions.py
spacetraders/api/fleet/__init__.py
spacetraders/api/fleet/create_chart.py
spacetraders/api/fleet/create_ship_ship_scan.py
spacetraders/api/fleet/create_ship_system_scan.py
spacetraders/api/fleet/create_ship_waypoint_scan.py
spacetraders/api/fleet/create_survey.py
spacetraders/api/fleet/dock_ship.py
spacetraders/api/fleet/extract_resources.py
spacetraders/api/fleet/extract_resources_with_survey.py
spacetraders/api/fleet/get_mounts.py
spacetraders/api/fleet/get_my_ship.py
spacetraders/api/fleet/get_my_ship_cargo.py
spacetraders/api/fleet/get_my_ships.py
spacetraders/api/fleet/get_ship_cooldown.py
spacetraders/api/fleet/get_ship_nav.py
spacetraders/api/fleet/install_mount.py
spacetraders/api/fleet/jettison.py
spacetraders/api/fleet/jump_ship.py
spacetraders/api/fleet/navigate_ship.py
spacetraders/api/fleet/negotiate_contract.py
spacetraders/api/fleet/orbit_ship.py
spacetraders/api/fleet/patch_ship_nav.py
spacetraders/api/fleet/purchase_cargo.py
spacetraders/api/fleet/purchase_ship.py
spacetraders/api/fleet/refuel_ship.py
spacetraders/api/fleet/remove_mount.py
spacetraders/api/fleet/sell_cargo.py
spacetraders/api/fleet/ship_refine.py
spacetraders/api/fleet/siphon_resources.py
spacetraders/api/fleet/transfer_cargo.py
spacetraders/api/fleet/warp_ship.py
spacetraders-0.10.0.dist-info/METADATA
spacetraders-0.10.0.dist-info/WHEEL
spacetraders-0.10.0.dist-info/RECORD
