Metadata-Version: 2.1
Name: spacetraders
Version: 0.10.0
Summary: Python API for Space Traders
License: Apache-2.0
Author: Marco Ceppi
Author-email: marco@ceppi.net
Requires-Python: >=3.11,<4.0
Classifier: License :: OSI Approved :: Apache Software License
Classifier: Programming Language :: Python :: 3
Classifier: Programming Language :: Python :: 3.11
Classifier: Programming Language :: Python :: 3.12
Requires-Dist: attrs (>=21.3.0)
Requires-Dist: httpx (>=0.24.0,<0.25.0)
Requires-Dist: pydantic (>=1.10.7,<2.0.0)
Requires-Dist: python-dateutil (>=2.8.2,<3.0.0)
